tnz_mcp
