Metadata-Version: 2.4
Name: tnz_mcp
Version: 0.1.1
Summary: MCP server for TNZ API integration with Claude Desktop and Gemini CLI
Author: TNZ Group
License: MIT
Classifier: Programming Language :: Python :: 3
Classifier: Programming Language :: Python :: 3.10
Classifier: Programming Language :: Python :: 3.11
Classifier: Programming Language :: Python :: 3.12
Classifier: Programming Language :: Python :: 3.13
Classifier: Operating System :: OS Independent
Requires-Python: <3.14,>=3.10
License-File: LICENSE
Requires-Dist: tnzapi>=2.4.2
Requires-Dist: mcp>=1.0.0
Dynamic: license-file
